{
  "posts": [
    {
      "title": "some post",
      "body": "some post",
      "id": 11
    },
    {
      "title": "another post",
      "body": "another post",
      "id": 12
    },
    {
      "title": "one else",
      "body": "one else",
      "id": 13
    },
    {
      "title": "",
      "body": "some post",
      "id": 14
    },
    {
      "title": "",
      "body": "one else",
      "id": 15
    },
    {
      "title": "one more",
      "body": "one more",
      "id": 16
    },
    {
      "title": "else",
      "body": "else",
      "id": 17
    },
    {
      "title": "more posts ...",
      "body": "more posts ...",
      "id": 18
    },
    {
      "title": "",
      "body": "what else",
      "id": 19
    },
    {
      "title": "make more posts",
      "body": "make more posts",
      "id": 20
    },
    {
      "title": "finish it",
      "body": "finish it",
      "id": 22
    },
    {
      "title": "lol",
      "body": "lol",
      "id": 23
    }
  ],
  "comments": [],
  "profile": {
    "name": "typicode"
  }
}